metrics.py
jmetrics-1.0.3.dist-info/METADATA
jmetrics-1.0.3.dist-info/WHEEL
jmetrics-1.0.3.dist-info/top_level.txt
jmetrics-1.0.3.dist-info/RECORD
